Aipixy/__init__.py
Aipixy/aipixy.py
Aipixy-1.0.0.dist-info/METADATA
Aipixy-1.0.0.dist-info/WHEEL
Aipixy-1.0.0.dist-info/top_level.txt
Aipixy-1.0.0.dist-info/RECORD
