Metadata-Version: 2.1
Name: Aipixy
Version: 1.0.0
Summary: A Python library for the Aipixy API, enabling the generation of personalized and dynamic clone videos.
Home-page: https://github.com/DanArbib/Aipixy-Python
Author: Dan Arbib
Author-email: support@aipixy.com
License: UNKNOWN
Platform: UNKNOWN
Requires-Dist: requests
